sdk_248/__init__.py
sdk_248/py.typed
sdk_248/db/__init__.py
sdk_248/db/mongo.py
sdk_248/db/postgres.py
sdk_248/models/__init__.py
sdk_248/models/enums.py
sdk_248/models/mongo/__init__.py
sdk_248/models/mongo/action_run.py
sdk_248/models/mongo/campaign.py
sdk_248/models/mongo/lead.py
sdk_248/models/mongo/node.py
sdk_248/models/postgres/__init__.py
sdk_248/models/postgres/organization.py
sdk_248/schemas/__init__.py
sdk_248/schemas/organization.py
sdk_248/schemas/smartlead/__init__.py
sdk_248/schemas/smartlead/request.py
sdk_248/schemas/smartlead/response.py
sdk_248/schemas/smartlead/validators.py
sdk_248/schemas/smartlead/webhook.py
248_sdk-0.1.0.dist-info/METADATA
248_sdk-0.1.0.dist-info/WHEEL
248_sdk-0.1.0.dist-info/RECORD
