Metadata-Version: 2.4
Name: 248-sdk
Version: 0.1.0
Summary: Shared SDK for 248 products - MongoDB models, PostgreSQL models, and SmartLead schemas
Project-URL: Repository, https://github.com/248ai/248-sdk
Author-email: Wenzo Rithelly <rithellyenzo@gmail.com>
License: MIT
Keywords: beanie,mongodb,postgresql,sdk,smartlead,sqlalchemy
Classifier: Development Status :: 4 - Beta
Classifier: Intended Audience :: Developers
Classifier: License :: OSI Approved :: MIT License
Classifier: Programming Language :: Python :: 3
Classifier: Programming Language :: Python :: 3.10
Classifier: Programming Language :: Python :: 3.11
Classifier: Programming Language :: Python :: 3.12
Classifier: Typing :: Typed
Requires-Python: >=3.10
Requires-Dist: beanie<3.0.0,>=2.0.1
Requires-Dist: motor<4.0.0,>=3.3.0
Requires-Dist: pydantic<3.0.0,>=2.0.0
Requires-Dist: sqlalchemy<3.0.0,>=2.0.0
Provides-Extra: all
Requires-Dist: mypy>=1.8.0; extra == 'all'
Requires-Dist: psycopg2-binary<3.0.0,>=2.9.0; extra == 'all'
Requires-Dist: pytest-asyncio>=0.23.0; extra == 'all'
Requires-Dist: pytest-cov>=4.0.0; extra == 'all'
Requires-Dist: pytest>=8.0.0; extra == 'all'
Requires-Dist: ruff>=0.2.0; extra == 'all'
Provides-Extra: asyncpg
Requires-Dist: asyncpg<1.0.0,>=0.29.0; extra == 'asyncpg'
Provides-Extra: dev
Requires-Dist: mypy>=1.8.0; extra == 'dev'
Requires-Dist: pytest-asyncio>=0.23.0; extra == 'dev'
Requires-Dist: pytest-cov>=4.0.0; extra == 'dev'
Requires-Dist: pytest>=8.0.0; extra == 'dev'
Requires-Dist: ruff>=0.2.0; extra == 'dev'
Provides-Extra: postgres
Requires-Dist: psycopg2-binary<3.0.0,>=2.9.0; extra == 'postgres'
